alibabacloud_ft20180713/__init__.py
alibabacloud_ft20180713/client.py
alibabacloud_ft20180713/models.py
alibabacloud_ft20180713-4.1.2.dist-info/LICENSE
alibabacloud_ft20180713-4.1.2.dist-info/METADATA
alibabacloud_ft20180713-4.1.2.dist-info/WHEEL
alibabacloud_ft20180713-4.1.2.dist-info/top_level.txt
alibabacloud_ft20180713-4.1.2.dist-info/RECORD
